lightkube_extensions/__init__.py
lightkube_extensions/batch/__init__.py
lightkube_extensions/batch/_kubernetes_resource_manager.py
lightkube_extensions/batch/_many.py
lightkube_extensions/mocking/__init__.py
lightkube_extensions/mocking/_response.py
lightkube_extensions/types/__init__.py
lightkube_extensions/types/_aggregate_types.py
lightkube_extensions/types/_custom_resource_types.py
lightkube_extensions-0.3.0.dist-info/licenses/LICENSE
lightkube_extensions-0.3.0.dist-info/METADATA
lightkube_extensions-0.3.0.dist-info/WHEEL
lightkube_extensions-0.3.0.dist-info/top_level.txt
lightkube_extensions-0.3.0.dist-info/RECORD
