Metadata-Version: 2.4
Name: lightkube-extensions
Version: 0.3.0
Summary: A collection of helpers and shared code for using Lightkube.
Home-page: https://github.com/canonical/lightkube-extensions
Author: Canonical Observability Team
License:                                  Apache License
Classifier: Programming Language :: Python :: 3
Classifier: Operating System :: OS Independent
Requires-Python: ~=3.8
License-File: LICENSE
Requires-Dist: lightkube>=0.11.0
Requires-Dist: jinja2
Dynamic: license-file
